MorseCode/__init__.py
MorseCode/morsecode.py
MorseCode2-0.0.3.dist-info/LICENSE
MorseCode2-0.0.3.dist-info/METADATA
MorseCode2-0.0.3.dist-info/WHEEL
MorseCode2-0.0.3.dist-info/top_level.txt
MorseCode2-0.0.3.dist-info/RECORD
