Metadata-Version: 2.1
Name: MorseCode2
Version: 0.0.3
Summary: Simple translations into morse code
Home-page: https://github.com/Oscar-Hogben/Morse-Code
Author: Oscar Hogben
Author-email: oscarhogben@gmail.com
License: UNKNOWN
Project-URL: Bug Tracker, https://github.com/Oscar-Hogben/Morse-Code/issues
Platform: UNKNOWN
Classifier: Programming Language :: Python :: 3
Classifier: License :: OSI Approved :: MIT License
Classifier: Operating System :: OS Independent
Requires-Python: >=3.6
